ws_one_stable/__init__.py
ws_one_stable/errors.py
ws_one_stable/main.py
ws_one_stable/server_test.py
ws_one_stable/settings.py
ws_one_stable/support_functions.py
ws_one_stable/terminals/__init__.py
ws_one_stable/terminals/A12E/__init__.py
ws_one_stable/terminals/A12E/functions.py
ws_one_stable/terminals/Art/__init__.py
ws_one_stable/terminals/Art/functions.py
ws_one_stable/terminals/Belo/__init__.py
ws_one_stable/terminals/Belo/functions.py
ws_one_stable/terminals/CAS/__init__.py
ws_one_stable/terminals/CAS/functions.py
ws_one_stable/terminals/CAS_CL-200A/__init__.py
ws_one_stable/terminals/CAS_CL-200A/functions.py
ws_one_stable/terminals/None/__init__.py
ws_one_stable/terminals/None/functions.py
ws_one_stable/terminals/TB_003/__init__.py
ws_one_stable/terminals/TB_003/functions.py
ws_one_stable/terminals/TB_011/__init__.py
ws_one_stable/terminals/TB_011/functions.py
ws_one_stable/terminals/Uvzo/__init__.py
ws_one_stable/terminals/Uvzo/functions.py
ws_one_stable/terminals/middle_mi010/__init__.py
ws_one_stable/terminals/middle_mi010/functions.py
ws_one_stable/terminals/monolit/__init__.py
ws_one_stable/terminals/monolit/functions.py
ws_one_stable/tests/__init__.py
ws_one_stable/tests/client_test.py
ws_one_stable/tests/settings_test.py
ws_one_stable/tests/support_functions_tests.py
ws_one-1.14.2.dist-info/LICENSE
ws_one-1.14.2.dist-info/METADATA
ws_one-1.14.2.dist-info/WHEEL
ws_one-1.14.2.dist-info/top_level.txt
ws_one-1.14.2.dist-info/RECORD
