Metadata-Version: 2.1
Name: ws-one
Version: 1.14.2
Author: PunchyArchy
Author-email: ksmdrmvscthny@gmail.com
License-File: LICENSE
Requires-Dist: pyserial
Requires-Dist: pds-one ==1.6.2
